code_editor_pro/__init__.py
code_editor_pro/__main__.py
code_editor_pro/cli.py
code_editor_pro/core/__init__.py
code_editor_pro/core/analyzer.py
code_editor_pro/core/cache.py
code_editor_pro/core/editor.py
code_editor_pro/core/error_parser.py
code_editor_pro/core/executor.py
code_editor_pro/core/generator.py
code_editor_pro/core/git_client.py
code_editor_pro/core/intellisense.py
code_editor_pro/core/lsp_client.py
code_editor_pro/core/parser.py
code_editor_pro/core/refactor.py
code_editor_pro/core/searcher.py
code_editor_pro/data/__init__.py
code_editor_pro/languages/__init__.py
code_editor_pro/languages/python.py
code_editor_pro/models.py
code_editor_pro/project/__init__.py
code_editor_pro/project/database.py
code_editor_pro/project/manager.py
code_editor_pro/schemas.py
code_editor_pro/server.py
code_editor_pro/templates/go_package.go.template
code_editor_pro/templates/python_class.py.template
code_editor_pro/templates/python_function.py.template
code_editor_pro/templates/python_test.py.template
code_editor_pro/templates/rust_module.rs.template
code_editor_pro/templates/typescript_component.tsx.template
code_editor_pro-0.1.0.dist-info/WHEEL
code_editor_pro-0.1.0.dist-info/entry_points.txt
code_editor_pro-0.1.0.dist-info/METADATA
code_editor_pro-0.1.0.dist-info/RECORD
