Metadata-Version: 2.3
Name: code-editor-pro
Version: 0.1.0
Summary: Advanced MCP code editor with multi-language support, optimized for Claude Sonnet 4.5
Keywords: mcp,code-editor,lsp,tree-sitter,claude,ai,code-analysis
Author: Björn Bethge
Author-email: Björn Bethge <bjoern.bethge@gmail.com>
License: MIT
Classifier: Development Status :: 4 - Beta
Classifier: Intended Audience :: Developers
Classifier: License :: OSI Approved :: MIT License
Classifier: Programming Language :: Python :: 3
Classifier: Programming Language :: Python :: 3.11
Classifier: Programming Language :: Python :: 3.12
Classifier: Topic :: Software Development :: Libraries :: Python Modules
Classifier: Topic :: Text Editors :: Integrated Development Environments (IDE)
Requires-Dist: mcp>=1.14.1
Requires-Dist: tree-sitter-languages>=1.10.2
Requires-Dist: jedi>=0.19.2
Requires-Dist: black>=25.9.0
Requires-Dist: ruff>=0.8.0
Requires-Dist: pydantic>=2.0.0
Requires-Dist: loguru>=0.7.0
Requires-Dist: click>=8.1.0
Requires-Dist: gitpython>=3.1.40
Requires-Dist: psutil>=5.9.0
Requires-Dist: pygls>=1.0.0
Requires-Dist: redis>=5.0.0 ; extra == 'cache'
Requires-Dist: pytest>=8.0.0 ; extra == 'dev'
Requires-Dist: pytest-cov>=4.1.0 ; extra == 'dev'
Requires-Dist: gitpython>=3.1.40 ; extra == 'git'
Requires-Dist: pygls>=1.0.0 ; extra == 'lsp'
Requires-Python: >=3.11
Provides-Extra: cache
Provides-Extra: dev
Provides-Extra: git
Provides-Extra: lsp
